_frankx.cpython-37m-x86_64-linux-gnu.so
pyaffx.cpython-37m-x86_64-linux-gnu.so
frankx.libs/libfranka-9c00d6c5.so.0.9.0
frankx.libs/libPocoNet-ac8eb170.so.31
frankx.libs/libpcre-9513aab5.so.1.2.0
frankx.libs/libPocoFoundation-c26869a6.so.31
frankx/gripper.py
frankx/__init__.py
frankx/robot.py
frankx-0.2.0.dist-info/WHEEL
frankx-0.2.0.dist-info/top_level.txt
frankx-0.2.0.dist-info/METADATA
frankx-0.2.0.dist-info/RECORD
frankx-0.2.0.dist-info/LICENSE
