Metadata-Version: 2.1
Name: frankx
Version: 0.2.0
Summary: High-Level Motion Library for the Franka Panda Robot
Home-page: https://github.com/pantor/frankx
Author: Lars Berscheid
Author-email: lars.berscheid@kit.edu
License: LGPL
Keywords: robot,robotics,trajectory-generation,motion-control
Platform: UNKNOWN
Classifier: Development Status :: 4 - Beta
Classifier: Intended Audience :: Science/Research
Classifier: Topic :: Scientific/Engineering
Classifier: License :: OSI Approved :: GNU Lesser General Public License v3 (LGPLv3)
Classifier: Programming Language :: C++
Requires-Python: >=3.6
License-File: LICENSE
